nemesispy/__init__.py
nemesispy/create_curves_example.py
nemesispy/demo_fit_eclipse.py
nemesispy/demo_fit_elipse.py
nemesispy/demo_fit_multiple_spectra.py
nemesispy/demo_fit_phase_curves.py
nemesispy/demo_gcm_roth.py
nemesispy/demo_gcm_tp.py
nemesispy/demo_uniform_disc.py
nemesispy/common/__init__.py
nemesispy/common/calc_hydrostat.py
nemesispy/common/calc_trig.py
nemesispy/common/constants.py
nemesispy/common/function_fit.py
nemesispy/common/helper.py
nemesispy/common/info_atom.py
nemesispy/common/info_mol.py
nemesispy/common/info_mol_id.py
nemesispy/common/interpolate_gcm.py
nemesispy/common/interpolate_star.py
nemesispy/data/__init__.py
nemesispy/data/helper.py
nemesispy/data/cia/exocia_hitran12_200-3800K.tab
nemesispy/data/gcm/__init__.py
nemesispy/data/gcm/format_roth.py
nemesispy/data/gcm/process_gcm.py
nemesispy/data/gcm/process_vivien.txt
nemesispy/data/gcm/process_vivien_mod.txt
nemesispy/data/gcm/fit_gcm/2pt5_fit.py
nemesispy/data/gcm/fit_gcm/__init__.py
nemesispy/data/gcm/fit_gcm/mpi_trial.py
nemesispy/data/gcm/wasp43b_vivien/AAbest_fit_20par.txt
nemesispy/data/gcm/wasp43b_vivien/AAbest_params_20par.txt
nemesispy/data/gcm/wasp43b_vivien/AAreadme.txt
nemesispy/data/gcm/wasp43b_vivien/__init__.py
nemesispy/data/gcm/wasp43b_vivien/best_fit_TP_2_stream_Guillot.txt
nemesispy/data/gcm/wasp43b_vivien/best_fit_TP_2_stream_Guillot_fixed_T_int.txt
nemesispy/data/gcm/wasp43b_vivien/best_fit_TP_3_stream_Guillot_fixed_T.txt
nemesispy/data/gcm/wasp43b_vivien/best_fit_params_2_stream_Guillot.txt
nemesispy/data/gcm/wasp43b_vivien/best_fit_params_2_stream_Guillot_fixed_T_int.txt
nemesispy/data/gcm/wasp43b_vivien/best_fit_params_3_stream_Guillot_fixed_T.txt
nemesispy/data/gcm/wasp43b_vivien/function_fit_log_T_int.py
nemesispy/data/gcm/wasp43b_vivien/function_fit_log_f.py
nemesispy/data/gcm/wasp43b_vivien/function_fit_log_gamma.py
nemesispy/data/gcm/wasp43b_vivien/function_fit_log_kappa.py
nemesispy/data/gcm/wasp43b_vivien/plot_compare_T_contour.py
nemesispy-0.0.10.dist-info/LICENSE
nemesispy-0.0.10.dist-info/METADATA
nemesispy-0.0.10.dist-info/WHEEL
nemesispy-0.0.10.dist-info/top_level.txt
nemesispy-0.0.10.dist-info/RECORD
