Metadata-Version: 2.1
Name: nemesispy
Version: 0.0.10
Summary: Tools for modelling exoplanet spectra
Home-page: https://github.com/Jingxuan97/nemesispy2022
Author: Jingxuan Yang
Author-email: jingxuanyang15@gmail.com
License-File: LICENSE
Requires-Dist: numpy
Requires-Dist: scipy
Requires-Dist: matplotlib
Requires-Dist: numba
